cbim_utils/__init__.py
cbim_utils/db_connection.py
cbim_utils/mysql_db_connection.py
cbim_utils-0.1.5.dist-info/LICENSE.txt
cbim_utils-0.1.5.dist-info/METADATA
cbim_utils-0.1.5.dist-info/WHEEL
cbim_utils-0.1.5.dist-info/top_level.txt
cbim_utils-0.1.5.dist-info/RECORD
